LICENSE
MANIFEST.in
README.md
setup.py
DrissionPage/__init__.py
DrissionPage/common.py
DrissionPage/errors.py
DrissionPage/items.py
DrissionPage/_base/base.py
DrissionPage/_base/base.pyi
DrissionPage/_base/browser.py
DrissionPage/_base/browser.pyi
DrissionPage/_base/driver.py
DrissionPage/_base/driver.pyi
DrissionPage/_configs/chromium_options.py
DrissionPage/_configs/chromium_options.pyi
DrissionPage/_configs/configs.ini
DrissionPage/_configs/options_manage.py
DrissionPage/_configs/options_manage.pyi
DrissionPage/_configs/session_options.py
DrissionPage/_configs/session_options.pyi
DrissionPage/_elements/chromium_element.py
DrissionPage/_elements/chromium_element.pyi
DrissionPage/_elements/none_element.py
DrissionPage/_elements/session_element.py
DrissionPage/_elements/session_element.pyi
DrissionPage/_functions/browser.py
DrissionPage/_functions/browser.pyi
DrissionPage/_functions/by.py
DrissionPage/_functions/cli.py
DrissionPage/_functions/keys.py
DrissionPage/_functions/keys.pyi
DrissionPage/_functions/locator.py
DrissionPage/_functions/locator.pyi
DrissionPage/_functions/settings.py
DrissionPage/_functions/tools.py
DrissionPage/_functions/tools.pyi
DrissionPage/_functions/web.py
DrissionPage/_functions/web.pyi
DrissionPage/_pages/chromium_base.py
DrissionPage/_pages/chromium_base.pyi
DrissionPage/_pages/chromium_frame.py
DrissionPage/_pages/chromium_frame.pyi
DrissionPage/_pages/chromium_page.py
DrissionPage/_pages/chromium_page.pyi
DrissionPage/_pages/chromium_tab.py
DrissionPage/_pages/chromium_tab.pyi
DrissionPage/_pages/session_page.py
DrissionPage/_pages/session_page.pyi
DrissionPage/_pages/web_page.py
DrissionPage/_pages/web_page.pyi
DrissionPage/_units/actions.py
DrissionPage/_units/actions.pyi
DrissionPage/_units/clicker.py
DrissionPage/_units/clicker.pyi
DrissionPage/_units/cookies_setter.py
DrissionPage/_units/cookies_setter.pyi
DrissionPage/_units/downloader.py
DrissionPage/_units/downloader.pyi
DrissionPage/_units/listener.py
DrissionPage_0503.egg-info/PKG-INFO
DrissionPage_0503.egg-info/SOURCES.txt
DrissionPage_0503.egg-info/dependency_links.txt
DrissionPage_0503.egg-info/entry_points.txt
DrissionPage_0503.egg-info/not-zip-safe
DrissionPage_0503.egg-info/requires.txt
DrissionPage_0503.egg-info/top_level.txt